pyLegoMario/ALL_RGB_CODES.json
pyLegoMario/__init__.py
pyLegoMario/background.png
pyLegoMario/icon.ico
pyLegoMario/lego_mario_data.py
pyLegoMario/mario.py
pyLegoMario/mario_GUI.py
pyLegoMario/pygame_mario.py
pyLegoMario-1.1.dist-info/METADATA
pyLegoMario-1.1.dist-info/WHEEL
pyLegoMario-1.1.dist-info/top_level.txt
pyLegoMario-1.1.dist-info/RECORD
