Metadata-Version: 2.1
Name: pyLegoMario
Version: 1.1
Summary: Module for handling connections with the Lego Mario toy
Author: Jamin Kauf, Bruno Hautzenberger
Author-email: jamin.kauf@yahoo.de
Project-URL: repository, https://github.com/Jackomatrus/pyLegoMario
Keywords: lego,python,super mario,lego mario,bluetooth
Classifier: Development Status :: 5 - Production/Stable
Classifier: Intended Audience :: Developers
Classifier: Programming Language :: Python :: 3
Classifier: Operating System :: Microsoft :: Windows
Classifier: License :: OSI Approved :: MIT License
Requires-Python: >=3.9
Requires-Dist: bleak
Requires-Dist: pathlib
Requires-Dist: asyncio
Requires-Dist: pillow
Requires-Dist: pygame
